nonebot_plugin_rtfm/__init__.py
nonebot_plugin_rtfm/algolia.py
nonebot_plugin_rtfm/config.py
nonebot_plugin_rtfm/parser.py
nonebot_plugin_rtfm/plugins.py
nonebot_plugin_rtfm-0.2.2.dist-info/LICENSE
nonebot_plugin_rtfm-0.2.2.dist-info/WHEEL
nonebot_plugin_rtfm-0.2.2.dist-info/METADATA
nonebot_plugin_rtfm-0.2.2.dist-info/RECORD
