Metadata-Version: 2.1
Name: nonebot-plugin-rtfm
Version: 0.2.2
Summary: A plugin for searching docs in QQ, use NoneBot and OneBot V11
Home-page: https://github.com/MingxuanGame/nonebot-plugin-rtfm
License: MIT
Keywords: nonebot,onebot,search,plugin,docs
Author: MingxuanGame
Author-email: MingxuanGame@outlook.com
Requires-Python: >=3.8,<4.0
Classifier: Development Status :: 3 - Alpha
Classifier: Environment :: Plugins
Classifier: Framework :: AsyncIO
Classifier: Framework :: Robot Framework
Classifier: Framework :: aiohttp
Classifier: Intended Audience :: Other Audience
Classifier: License :: OSI Approved :: MIT License
Classifier: Natural Language :: Chinese (Simplified)
Classifier: Programming Language :: Python :: 3
Classifier: Programming Language :: Python :: 3.10
Classifier: Programming Language :: Python :: 3.8
Classifier: Programming Language :: Python :: 3.9
Classifier: Topic :: Documentation
Requires-Dist: aiohttp (>=3.8.1,<4.0.0)
Requires-Dist: algoliasearch (>=2.6.1,<3.0.0)
Requires-Dist: async-timeout (>=4.0.2,<5.0.0)
Requires-Dist: nonebot-adapter-onebot (>=2.0.0-beta.1,<3.0.0)
Requires-Dist: nonebot2 (>=2.0.0-beta.2,<3.0.0)
Project-URL: Documentation, https://github.com/MingxuanGame/nonebot-plugin-rtfm/blob/master/README.md#命令
Project-URL: Repository, https://github.com/MingxuanGame/nonebot-plugin-rtfm
